<?xml version="1.0" encoding="utf-8"?>
<!DOCTYPE hibernate-mapping PUBLIC "-//Hibernate/Hibernate Mapping DTD 3.0//EN"
"http://hibernate.sourceforge.net/hibernate-mapping-3.0.dtd">
<!-- 
    Mapping file autogenerated by MyEclipse Persistence Tools
-->
<hibernate-mapping>
    <class name="dao.Wirinfo" table="wirinfo" catalog="client">
        <id name="id" type="java.lang.Integer">
            <column name="id" />
            <generator class="increment" />
        </id>
        <many-to-one name="caseinfo" class="dao.Caseinfo" fetch="select">
            <column name="caseinfo_id" not-null="true" />
        </many-to-one>
        <property name="itemid" type="java.lang.String">
            <column name="itemid" length="225" not-null="true" />
        </property>
        <property name="location" type="java.lang.String">
            <column name="location" length="45" />
        </property>
        <property name="latitude" type="java.lang.Double">
            <column name="latitude" precision="22" scale="0" />
        </property>
        <property name="longitude" type="java.lang.Double">
            <column name="longitude" precision="22" scale="0" />
        </property>
        <property name="region" type="java.lang.String">
            <column name="region" length="45" />
        </property>
        <property name="delayFactor" type="java.lang.Double">
            <column name="delayFactor" precision="22" scale="0" />
        </property>
        <property name="appointmentTime" type="java.lang.String">
            <column name="appointmentTime" length="45" />
        </property>
        <property name="consuming" type="java.lang.Double">
            <column name="consuming" precision="22" scale="0" />
        </property>
    </class>
</hibernate-mapping>
